{"Event": {"info": "OSINT - Does Your Mobile Anti-Virus App Protect or Infect You? The Truth Behind DU Antivirus Security", "Tag": [{"colour": "#e7007d", "exportable": true, "name": "workflow:state=\"incomplete\""}, {"colour": "#ffffff", "exportable": true, "name": "tlp:white"}, {"colour": "#850048", "exportable": true, "name": "workflow:todo=\"create-missing-misp-galaxy-cluster-values\""}, {"colour": "#7a0042", "exportable": true, "name": "workflow:todo=\"create-missing-misp-galaxy-cluster\""}], "publish_timestamp": "0", "timestamp": "1513930883", "analysis": "2", "Attribute": [{"comment": "", "category": "External analysis", "uuid": "5a3bd303-7b7c-4c96-9715-4d1b950d210f", "timestamp": "1513870083", "to_ids": false, "value": "https://research.checkpoint.com/mobile-anti-virus-app-protect-infect-truth-behind-du-antivirus-security/", "disable_correlation": false, "object_relation": null, "type": "link"}], "extends_uuid": "", "published": false, "date": "2017-09-18", "Orgc": {"uuid": "55f6ea5e-2c60-40e5-964f-47a8950d210f", "name": "CIRCL"}, "threat_level_id": "3", "uuid": "5a3bd2f3-3360-43cf-a015-404d950d210f"}}