{
  "Event": {
    "date": "2018-05-24",
    "timestamp": "1535035985",
    "analysis": "2",
    "uuid": "5b06a4b4-6e74-40b8-ae95-9fc10acd0835",
    "published": true,
    "extends_uuid": "",
    "publish_timestamp": "1535036079",
    "info": "Emotet - 5/21/2018",
    "threat_level_id": "3",
    "Orgc": {
      "uuid": "5a68c02d-959c-4c8a-a571-0dcac0a8060a",
      "name": "Synovus Financial"
    },
    "Tag": [
      {
        "colour": "#ffffff",
        "name": "tlp:white"
      },
      {
        "colour": "#0088cc",
        "name": "misp-galaxy:tool=\"Emotet\""
      }
    ],
    "Attribute": [
      {
        "category": "Payload delivery",
        "timestamp": "1527162039",
        "comment": "",
        "uuid": "7b135136-7931-4be5-99fd-0535af09574f",
        "value": "33da043e770f5d78ca3b3d97863ca527",
        "to_ids": true,
        "type": "md5",
        "deleted": false,
        "disable_correlation": false
      },
      {
        "category": "Payload delivery",
        "timestamp": "1527162042",
        "comment": "",
        "uuid": "fe42e04f-7e58-4f1e-b8cc-cb665e314902",
        "value": "204873e8e3deeb549ae920b27d5258cf",
        "to_ids": true,
        "type": "md5",
        "deleted": false,
        "disable_correlation": false
      },
      {
        "category": "Payload delivery",
        "timestamp": "1527162046",
        "comment": "",
        "uuid": "eea035ef-6290-4240-b74f-aef13d193cb9",
        "value": "9f70fa70b468f332bb7ade24dfe0c3c7",
        "to_ids": true,
        "type": "md5",
        "deleted": false,
        "disable_correlation": false
      },
      {
        "category": "Payload delivery",
        "timestamp": "1527162049",
        "comment": "",
        "uuid": "3101104f-45df-4f00-9dbf-fabc6b9deb0c",
        "value": "22b2e23fbe67d3ccefbcf99b076ed3aa",
        "to_ids": true,
        "type": "md5",
        "deleted": false,
        "disable_correlation": false
      },
      {
        "category": "Network activity",
        "timestamp": "1535035984",
        "comment": "",
        "uuid": "ad53a93e-facb-4ad5-9f85-a22214326190",
        "value": "https://protonmail.com",
        "to_ids": false,
        "type": "url",
        "deleted": false,
        "disable_correlation": false
      },
      {
        "category": "Network activity",
        "timestamp": "1527162073",
        "comment": "",
        "uuid": "92a8762d-a38e-4c99-b691-7b1cd9e32f9a",
        "value": "http://deist-online.de/ups.com/WebTracking/KKV-71871574417210/",
        "to_ids": true,
        "type": "url",
        "deleted": false,
        "disable_correlation": false
      },
      {
        "category": "Network activity",
        "timestamp": "1527162079",
        "comment": "",
        "uuid": "0da51511-bce8-4977-9c05-96df30e9566b",
        "value": "http://edv-salz.de/STATUS/Please-pull-invoice-547885/",
        "to_ids": true,
        "type": "url",
        "deleted": false,
        "disable_correlation": false
      },
      {
        "category": "Network activity",
        "timestamp": "1527162085",
        "comment": "",
        "uuid": "3c1cc519-541a-4a9a-b0b2-00ba1f32fe74",
        "value": "http://kflife.com/aspnet_client/system_web/4_0_30319/Client/Pay-Invoice/",
        "to_ids": true,
        "type": "url",
        "deleted": false,
        "disable_correlation": false
      },
      {
        "category": "Network activity",
        "timestamp": "1527162091",
        "comment": "",
        "uuid": "bd7df7e6-5180-48fe-8cf3-23fb61b0f21b",
        "value": "http://ivanrivera.com/Client/Invoice-152185/",
        "to_ids": true,
        "type": "url",
        "deleted": false,
        "disable_correlation": false
      },
      {
        "category": "Network activity",
        "timestamp": "1527162097",
        "comment": "",
        "uuid": "993cf2a4-6c32-4bff-91ac-539d4e158628",
        "value": "http://houselight.com.br/STATUS/Invoice-67059306-Invoice-date-052118-Order-no-95855818767/",
        "to_ids": true,
        "type": "url",
        "deleted": false,
        "disable_correlation": false
      },
      {
        "category": "Network activity",
        "timestamp": "1527162103",
        "comment": "",
        "uuid": "40cf6878-f6e8-43c5-b4c5-8c3b4fcfedc3",
        "value": "http://onfarmsystems.com/ups.com/WebTracking/TRF-09391329/",
        "to_ids": true,
        "type": "url",
        "deleted": false,
        "disable_correlation": false
      },
      {
        "category": "Network activity",
        "timestamp": "1527162109",
        "comment": "",
        "uuid": "906812fa-772c-493d-9929-583ed3eff156",
        "value": "http://hellogrid.com/STATUS/Invoice-09969006-Invoice-date-052118-Order-no-41574537247/",
        "to_ids": true,
        "type": "url",
        "deleted": false,
        "disable_correlation": false
      },
      {
        "category": "Network activity",
        "timestamp": "1527162115",
        "comment": "",
        "uuid": "d43f4d7d-dabe-4b5e-b659-0bbc1de8a35d",
        "value": "http://kjg-schiefbahn.de/STATUS/Direct-Deposit-Notice/",
        "to_ids": true,
        "type": "url",
        "deleted": false,
        "disable_correlation": false
      },
      {
        "category": "Network activity",
        "timestamp": "1527162121",
        "comment": "",
        "uuid": "8c1ee6ee-772a-4945-9eab-3103cb146ddd",
        "value": "http://cnajs.com/FILE/Invoice-047243/",
        "to_ids": true,
        "type": "url",
        "deleted": false,
        "disable_correlation": false
      },
      {
        "category": "Network activity",
        "timestamp": "1527162127",
        "comment": "",
        "uuid": "3d905dd6-d1a5-4baf-bce2-6828b8fff767",
        "value": "http://ginca.jp/Client/INV4534915560523538361/",
        "to_ids": true,
        "type": "url",
        "deleted": false,
        "disable_correlation": false
      },
      {
        "category": "Network activity",
        "timestamp": "1527162133",
        "comment": "",
        "uuid": "2fecc582-61d4-4e3d-9760-2046fcf6130f",
        "value": "http://eurokarton.pl/js/ups.com/WebTracking/IZ-4156347217578/",
        "to_ids": true,
        "type": "url",
        "deleted": false,
        "disable_correlation": false
      },
      {
        "category": "Network activity",
        "timestamp": "1527162139",
        "comment": "",
        "uuid": "ca0331df-e7e8-4743-a550-9df5f93639e9",
        "value": "https://birgitdresel.de/ups.com/WebTracking/TJ-16728641/",
        "to_ids": true,
        "type": "url",
        "deleted": false,
        "disable_correlation": false
      },
      {
        "category": "Network activity",
        "timestamp": "1527162145",
        "comment": "",
        "uuid": "3c787c77-4fcf-417a-940b-4d5b65cdfd58",
        "value": "http://europlastic.de/STATUS/New-Invoice-WG92763-IW-78087/",
        "to_ids": true,
        "type": "url",
        "deleted": false,
        "disable_correlation": false
      },
      {
        "category": "Network activity",
        "timestamp": "1527162151",
        "comment": "",
        "uuid": "90de570a-3d6b-438e-8836-5e5d20315b18",
        "value": "https://kadow.de/STATUS/New-Invoice-CY56039-ZW-4575/",
        "to_ids": true,
        "type": "url",
        "deleted": false,
        "disable_correlation": false
      },
      {
        "category": "Network activity",
        "timestamp": "1527162157",
        "comment": "",
        "uuid": "d3387d17-7548-44fc-b158-2e1748fec0eb",
        "value": "http://leasefor.com/ups.com/WebTracking/BL-7933643910213/",
        "to_ids": true,
        "type": "url",
        "deleted": false,
        "disable_correlation": false
      },
      {
        "category": "Network activity",
        "timestamp": "1527162163",
        "comment": "",
        "uuid": "4366fdaa-3e1d-435a-ab53-78b1dced298f",
        "value": "http://liebner.de/ups.com/WebTracking/ZZR-29523172658673/",
        "to_ids": true,
        "type": "url",
        "deleted": false,
        "disable_correlation": false
      },
      {
        "category": "Network activity",
        "timestamp": "1527162169",
        "comment": "",
        "uuid": "9dafd2b0-0e8c-49d7-809c-4c0c112b7f77",
        "value": "http://fatafati.net/ups.com/WebTracking/DUV-6004272960517/",
        "to_ids": true,
        "type": "url",
        "deleted": false,
        "disable_correlation": false
      },
      {
        "category": "Network activity",
        "timestamp": "1527162175",
        "comment": "",
        "uuid": "790a1845-0e79-480f-b327-56808124942c",
        "value": "http://axiscook.com/FILE/Invoices/",
        "to_ids": true,
        "type": "url",
        "deleted": false,
        "disable_correlation": false
      },
      {
        "category": "Network activity",
        "timestamp": "1527162181",
        "comment": "",
        "uuid": "11747515-d7cf-4f5e-bc2a-99f7b918ff30",
        "value": "http://catbones.com/ups.com/WebTracking/UCC-7144476318/",
        "to_ids": true,
        "type": "url",
        "deleted": false,
        "disable_correlation": false
      },
      {
        "category": "Network activity",
        "timestamp": "1527162187",
        "comment": "",
        "uuid": "be97cb83-10b8-4ec3-b9c9-6dabbb77c8d4",
        "value": "http://h-itshop.de/ACCOUNT/Account-22050/",
        "to_ids": true,
        "type": "url",
        "deleted": false,
        "disable_correlation": false
      },
      {
        "category": "Network activity",
        "timestamp": "1527162193",
        "comment": "",
        "uuid": "0d6fd649-0fac-45a3-a39d-a60b903bb4d4",
        "value": "http://429days.com/Bq7lgGA/",
        "to_ids": true,
        "type": "url",
        "deleted": false,
        "disable_correlation": false
      },
      {
        "category": "Network activity",
        "timestamp": "1527162199",
        "comment": "",
        "uuid": "6ecfe54f-cfe8-4d1e-9ba0-8e1e62665a8d",
        "value": "http://hajdamowicz.com/I4UZR/",
        "to_ids": true,
        "type": "url",
        "deleted": false,
        "disable_correlation": false
      },
      {
        "category": "Network activity",
        "timestamp": "1527162205",
        "comment": "",
        "uuid": "ab5bfdb3-575f-4934-964e-d779297e49e5",
        "value": "http://ahrensgrabenhorst.de/32bzspb/",
        "to_ids": true,
        "type": "url",
        "deleted": false,
        "disable_correlation": false
      },
      {
        "category": "Network activity",
        "timestamp": "1527162211",
        "comment": "",
        "uuid": "cc28f33c-ccdb-4d47-bda9-563ef8ba4709",
        "value": "http://andrescal.com.ar/Xn9z/",
        "to_ids": true,
        "type": "url",
        "deleted": false,
        "disable_correlation": false
      },
      {
        "category": "Network activity",
        "timestamp": "1527162217",
        "comment": "",
        "uuid": "e7967451-e224-498e-a14d-ad06a75ff309",
        "value": "http://imagesbr.com/nW3HM/",
        "to_ids": true,
        "type": "url",
        "deleted": false,
        "disable_correlation": false
      },
      {
        "category": "Network activity",
        "timestamp": "1527162229",
        "comment": "",
        "uuid": "b752609e-c9c0-4d0a-b413-c12b96bcdc32",
        "value": "http://hisociety.at/Factura-7824771/",
        "to_ids": true,
        "type": "url",
        "deleted": false,
        "disable_correlation": false
      },
      {
        "category": "Network activity",
        "timestamp": "1527162235",
        "comment": "",
        "uuid": "e60e390c-443e-4f82-905e-d2e26731e1e3",
        "value": "http://jana-spreen.de/Correcciones/",
        "to_ids": true,
        "type": "url",
        "deleted": false,
        "disable_correlation": false
      },
      {
        "category": "Network activity",
        "timestamp": "1527162241",
        "comment": "",
        "uuid": "fb08b5fc-ba38-4453-90b9-58c56fc478b1",
        "value": "http://gerbrecha.com/Facturas-disponibles/",
        "to_ids": true,
        "type": "url",
        "deleted": false,
        "disable_correlation": false
      },
      {
        "category": "Network activity",
        "timestamp": "1527162247",
        "comment": "",
        "uuid": "b60ade76-7574-4389-b3ed-c42a475b475a",
        "value": "https://fotofolly.com/Factura-Correcciones-para-896674/",
        "to_ids": true,
        "type": "url",
        "deleted": false,
        "disable_correlation": false
      },
      {
        "category": "Network activity",
        "timestamp": "1527162253",
        "comment": "",
        "uuid": "8b95983d-9a6a-4934-9490-036eea3c223d",
        "value": "http://fantastrick.nl/Paid-Invoice/",
        "to_ids": true,
        "type": "url",
        "deleted": false,
        "disable_correlation": false
      },
      {
        "category": "Network activity",
        "timestamp": "1527162259",
        "comment": "",
        "uuid": "c8235eba-5062-4bb4-beb3-38601926a83c",
        "value": "http://www.toniruy.ru/Factura-por-descargas/",
        "to_ids": true,
        "type": "url",
        "deleted": false,
        "disable_correlation": false
      },
      {
        "category": "Network activity",
        "timestamp": "1527162265",
        "comment": "",
        "uuid": "d6771a70-2191-4198-852b-3be9071daa00",
        "value": "http://keithdaley.co.uk/wpp-app/Abierto-Pasado-Vencimiento-Pedidos/",
        "to_ids": true,
        "type": "url",
        "deleted": false,
        "disable_correlation": false
      },
      {
        "category": "Network activity",
        "timestamp": "1527162271",
        "comment": "",
        "uuid": "eafa06a4-c2d4-48bc-b91f-b93ef03a14aa",
        "value": "http://groupevl.ca/1-Pasado-Debida-Facturas/",
        "to_ids": true,
        "type": "url",
        "deleted": false,
        "disable_correlation": false
      },
      {
        "category": "Network activity",
        "timestamp": "1527162277",
        "comment": "",
        "uuid": "f5ac55d0-66e7-4e27-8db5-3b45a82eebeb",
        "value": "http://bunt.com/classifieds/session/Invoice-form/",
        "to_ids": true,
        "type": "url",
        "deleted": false,
        "disable_correlation": false
      },
      {
        "category": "Network activity",
        "timestamp": "1527162283",
        "comment": "",
        "uuid": "f6387846-5e79-47b0-83fb-80ecbd64bfcd",
        "value": "http://heathmarshallhorsemanship.com/Nueva-Factura/",
        "to_ids": true,
        "type": "url",
        "deleted": false,
        "disable_correlation": false
      },
      {
        "category": "Network activity",
        "timestamp": "1527162289",
        "comment": "",
        "uuid": "b48d8997-b832-4ee6-a803-cfe2c1dd0709",
        "value": "http://generalbikes.com/factura-recibo/",
        "to_ids": true,
        "type": "url",
        "deleted": false,
        "disable_correlation": false
      },
      {
        "category": "Network activity",
        "timestamp": "1527162295",
        "comment": "",
        "uuid": "b677b3e6-4841-498e-814b-655650e0ba53",
        "value": "http://larrysmith.com/Scan-40567/",
        "to_ids": true,
        "type": "url",
        "deleted": false,
        "disable_correlation": false
      },
      {
        "category": "Network activity",
        "timestamp": "1527162301",
        "comment": "",
        "uuid": "790d3d60-0642-40c5-8556-3b4e49778a5f",
        "value": "http://labmat.pl/Resumen-de-estados-de-cuenta/",
        "to_ids": true,
        "type": "url",
        "deleted": false,
        "disable_correlation": false
      },
      {
        "category": "Network activity",
        "timestamp": "1527162307",
        "comment": "",
        "uuid": "d33085f4-4a53-4fbe-959e-fa3961958b43",
        "value": "http://kunkel5.com/aspnet_client/Factura-por-descargas/",
        "to_ids": true,
        "type": "url",
        "deleted": false,
        "disable_correlation": false
      },
      {
        "category": "Network activity",
        "timestamp": "1527162313",
        "comment": "",
        "uuid": "7dc82997-0eae-401c-bb6f-4e069c0e47a9",
        "value": "http://flewer.pl/klasy/recordatorio/",
        "to_ids": true,
        "type": "url",
        "deleted": false,
        "disable_correlation": false
      },
      {
        "category": "Network activity",
        "timestamp": "1527162319",
        "comment": "",
        "uuid": "433df490-8552-4a9e-8544-d7680fa5a501",
        "value": "http://halcak.sk/Scan-35311/",
        "to_ids": true,
        "type": "url",
        "deleted": false,
        "disable_correlation": false
      },
      {
        "category": "Network activity",
        "timestamp": "1527162325",
        "comment": "",
        "uuid": "bff9ccc9-44a4-4fae-a32b-88cc406d0778",
        "value": "http://hygienic.co.th/components/Factura-Correcciones-para-552587/",
        "to_ids": true,
        "type": "url",
        "deleted": false,
        "disable_correlation": false
      },
      {
        "category": "Network activity",
        "timestamp": "1527162331",
        "comment": "",
        "uuid": "38de46aa-5c29-48b0-b203-c285f45d8714",
        "value": "http://data-gel.com/Service-Inv/",
        "to_ids": true,
        "type": "url",
        "deleted": false,
        "disable_correlation": false
      },
      {
        "category": "Network activity",
        "timestamp": "1527162338",
        "comment": "",
        "uuid": "e00fbf0e-f840-4c0e-8003-ab3ad1f34074",
        "value": "http://aqualuna.jp/Invoice-attached/",
        "to_ids": true,
        "type": "url",
        "deleted": false,
        "disable_correlation": false
      },
      {
        "category": "Network activity",
        "timestamp": "1527162344",
        "comment": "",
        "uuid": "45a0ef00-04ad-45a5-a244-545a76f93693",
        "value": "http://dievoigts.com/Invoice-attached/",
        "to_ids": true,
        "type": "url",
        "deleted": false,
        "disable_correlation": false
      },
      {
        "category": "Network activity",
        "timestamp": "1527162350",
        "comment": "",
        "uuid": "41e28f2e-a661-442c-a53e-acc235d250db",
        "value": "https://chergo.es/Outstanding-Invoices/",
        "to_ids": true,
        "type": "url",
        "deleted": false,
        "disable_correlation": false
      },
      {
        "category": "Network activity",
        "timestamp": "1527162356",
        "comment": "",
        "uuid": "4f6a8260-731e-4e5a-8430-8308a93c7530",
        "value": "http://chergo.es/Outstanding-Invoices/",
        "to_ids": true,
        "type": "url",
        "deleted": false,
        "disable_correlation": false
      },
      {
        "category": "Network activity",
        "timestamp": "1527162362",
        "comment": "",
        "uuid": "454a387c-f39d-4a6e-a225-e0ab846f30e5",
        "value": "http://contactclub.com/Facturas-pendientes/",
        "to_ids": true,
        "type": "url",
        "deleted": false,
        "disable_correlation": false
      },
      {
        "category": "Network activity",
        "timestamp": "1527162368",
        "comment": "",
        "uuid": "644f4699-a1df-4db5-b69b-1621c122a406",
        "value": "http://fotofolly.com/Factura-Correcciones-para-896674/",
        "to_ids": true,
        "type": "url",
        "deleted": false,
        "disable_correlation": false
      },
      {
        "category": "Network activity",
        "timestamp": "1527162374",
        "comment": "",
        "uuid": "b49bed1d-4cd6-450c-9ea2-ea1ab71614c1",
        "value": "http://casamatamatera.it/0Vqt4/",
        "to_ids": true,
        "type": "url",
        "deleted": false,
        "disable_correlation": false
      },
      {
        "category": "Network activity",
        "timestamp": "1527162380",
        "comment": "",
        "uuid": "eaa9dd10-68c6-48b3-8806-0616398970e5",
        "value": "http://intenseit.com.au/grQ97kNdN/",
        "to_ids": true,
        "type": "url",
        "deleted": false,
        "disable_correlation": false
      },
      {
        "category": "Network activity",
        "timestamp": "1527162386",
        "comment": "",
        "uuid": "c72f02cc-7da2-4c7c-bd0c-7c4e6bdfbd5e",
        "value": "http://gsimaging.net/nIzqr7q7e/",
        "to_ids": true,
        "type": "url",
        "deleted": false,
        "disable_correlation": false
      },
      {
        "category": "Network activity",
        "timestamp": "1527162392",
        "comment": "",
        "uuid": "7ac3b791-8acc-4f61-be79-ef3cab1ad3be",
        "value": "http://jvmusic.ca/VDTkN/",
        "to_ids": true,
        "type": "url",
        "deleted": false,
        "disable_correlation": false
      },
      {
        "category": "Network activity",
        "timestamp": "1527162399",
        "comment": "",
        "uuid": "af7c7b13-716a-4850-9d79-043d27ebd747",
        "value": "http://websteroids.ro/W0Xul1jAj/",
        "to_ids": true,
        "type": "url",
        "deleted": false,
        "disable_correlation": false
      },
      {
        "category": "Network activity",
        "timestamp": "1527162411",
        "comment": "",
        "uuid": "313b9f36-c656-46fe-8847-5eb6b2b69793",
        "value": "http://solid-unit.com/DOC/Invoice-60094596-Invoice-date-052118-Order-no-3911666675/",
        "to_ids": true,
        "type": "url",
        "deleted": false,
        "disable_correlation": false
      },
      {
        "category": "Network activity",
        "timestamp": "1527162417",
        "comment": "",
        "uuid": "5f45baf4-0152-465e-a879-a15ef9979c71",
        "value": "http://charihome.com/Client/Invoice/",
        "to_ids": true,
        "type": "url",
        "deleted": false,
        "disable_correlation": false
      },
      {
        "category": "Network activity",
        "timestamp": "1527162434",
        "comment": "",
        "uuid": "5518616e-3305-45db-9c3b-d27567c99810",
        "value": "http://gips-walkenried.de/STATUS/Invoice-93224/",
        "to_ids": true,
        "type": "url",
        "deleted": false,
        "disable_correlation": false
      },
      {
        "category": "Network activity",
        "timestamp": "1527162476",
        "comment": "",
        "uuid": "653a06ef-a2c9-4313-9258-6bf392a6858e",
        "value": "http://fischer-itsolutions.de/Client/ACCOUNT080862/",
        "to_ids": true,
        "type": "url",
        "deleted": false,
        "disable_correlation": false
      },
      {
        "category": "Network activity",
        "timestamp": "1527162483",
        "comment": "",
        "uuid": "71f630be-cd2f-48c1-a2bc-f65fc4a2a6e0",
        "value": "http://itmdf.de/ups.com/WebTracking/FS-17532695/",
        "to_ids": true,
        "type": "url",
        "deleted": false,
        "disable_correlation": false
      },
      {
        "category": "Network activity",
        "timestamp": "1527162489",
        "comment": "",
        "uuid": "4371d231-e8ff-4ac4-97d2-26f7b7e6795b",
        "value": "http://cyzic.com/STATUS/Auditor-of-State-Notification-of-EFT-Deposit/",
        "to_ids": true,
        "type": "url",
        "deleted": false,
        "disable_correlation": false
      },
      {
        "category": "Network activity",
        "timestamp": "1527162495",
        "comment": "",
        "uuid": "95c3ecee-0d29-4bee-9963-27adee8927b2",
        "value": "https://juergen-dietel.de/Client/Auditor-of-State-Notification-of-EFT-Deposit/",
        "to_ids": true,
        "type": "url",
        "deleted": false,
        "disable_correlation": false
      },
      {
        "category": "Network activity",
        "timestamp": "1527162502",
        "comment": "",
        "uuid": "01633a75-3ed2-4cd5-a7a8-15e340774316",
        "value": "http://crazy-systems.com/ups.com/WebTracking/SEC-001569551712321/",
        "to_ids": true,
        "type": "url",
        "deleted": false,
        "disable_correlation": false
      },
      {
        "category": "Network activity",
        "timestamp": "1527162508",
        "comment": "",
        "uuid": "549143ed-734c-4efc-bd48-fdfcf7101fe7",
        "value": "http://hellmuth-worbs.de/ups.com/WebTracking/XWM-026895014/",
        "to_ids": true,
        "type": "url",
        "deleted": false,
        "disable_correlation": false
      },
      {
        "category": "Network activity",
        "timestamp": "1527162514",
        "comment": "",
        "uuid": "98b3177c-57d8-4e5b-827c-f2787c91a5f7",
        "value": "http://janpolet.nl/Client/Auditor-of-State-Notification-of-EFT-Deposit/",
        "to_ids": true,
        "type": "url",
        "deleted": false,
        "disable_correlation": false
      },
      {
        "category": "Network activity",
        "timestamp": "1527162520",
        "comment": "",
        "uuid": "6967fb57-57dd-4ee0-bfd7-0571dbd93e61",
        "value": "http://bechner.com/ups.com/WebTracking/IFI-8709813039/",
        "to_ids": true,
        "type": "url",
        "deleted": false,
        "disable_correlation": false
      },
      {
        "category": "Network activity",
        "timestamp": "1527162526",
        "comment": "",
        "uuid": "d5c1cb2d-cfc8-4c6d-9ee9-0b4ee49ae283",
        "value": "http://innervation.com/ups.com/WebTracking/GCV-192478446701844/",
        "to_ids": true,
        "type": "url",
        "deleted": false,
        "disable_correlation": false
      },
      {
        "category": "Network activity",
        "timestamp": "1527162532",
        "comment": "",
        "uuid": "b7d91d7e-a054-4083-8ef7-9feb4560e85d",
        "value": "http://jamesddunn.com/ups.com/WebTracking/VUE-130658434680/",
        "to_ids": true,
        "type": "url",
        "deleted": false,
        "disable_correlation": false
      },
      {
        "category": "Network activity",
        "timestamp": "1527162539",
        "comment": "",
        "uuid": "1886ad83-17ca-4f6f-a548-e1fe2ec94225",
        "value": "http://cedecarmona.com/ups.com/WebTracking/MOC-98465082/",
        "to_ids": true,
        "type": "url",
        "deleted": false,
        "disable_correlation": false
      },
      {
        "category": "Network activity",
        "timestamp": "1527162551",
        "comment": "",
        "uuid": "0c6c42f0-08b2-4ee1-aedf-27db7b605367",
        "value": "https://ibkrentel.de/STATUS/Invoices/",
        "to_ids": true,
        "type": "url",
        "deleted": false,
        "disable_correlation": false
      },
      {
        "category": "Network activity",
        "timestamp": "1527162557",
        "comment": "",
        "uuid": "d8a017de-d31c-4a07-a33b-067ec99d1cff",
        "value": "http://iyioglu.com/jKmV/",
        "to_ids": true,
        "type": "url",
        "deleted": false,
        "disable_correlation": false
      },
      {
        "category": "Network activity",
        "timestamp": "1527162563",
        "comment": "",
        "uuid": "8de74505-0cb9-4ea2-87b2-f6fe15ab3648",
        "value": "http://dmsta.com/DG9zb/",
        "to_ids": true,
        "type": "url",
        "deleted": false,
        "disable_correlation": false
      },
      {
        "category": "Network activity",
        "timestamp": "1527162569",
        "comment": "",
        "uuid": "ef2d4f82-27fe-4cae-a725-4fbacb2add63",
        "value": "https://averin.pro/j7oL/",
        "to_ids": true,
        "type": "url",
        "deleted": false,
        "disable_correlation": false
      },
      {
        "category": "Network activity",
        "timestamp": "1527162575",
        "comment": "",
        "uuid": "c41f0a0b-5db7-49db-bf95-f423dbffad00",
        "value": "http://davehale.co.uk/gpRiJY/",
        "to_ids": true,
        "type": "url",
        "deleted": false,
        "disable_correlation": false
      },
      {
        "category": "Network activity",
        "timestamp": "1527162581",
        "comment": "",
        "uuid": "73ea8a7e-f9f4-49f0-9f88-4c551517b5a7",
        "value": "http://FlorissantFire.com/aspnet_client/H068W54/",
        "to_ids": true,
        "type": "url",
        "deleted": false,
        "disable_correlation": false
      },
      {
        "category": "Network activity",
        "timestamp": "1527162587",
        "comment": "",
        "uuid": "d1728be1-7f44-41ad-9c9a-7f5a5117253a",
        "value": "http://fredmeseck.com/ups.com/WebTracking/WZ-582819876301/",
        "to_ids": true,
        "type": "url",
        "deleted": false,
        "disable_correlation": false
      },
      {
        "category": "Network activity",
        "timestamp": "1527162593",
        "comment": "",
        "uuid": "3d521c99-2938-466e-90d2-ab7570f2ea22",
        "value": "http://edcentric.org/ups.com/WebTracking/JG-97917329625936/",
        "to_ids": true,
        "type": "url",
        "deleted": false,
        "disable_correlation": false
      },
      {
        "category": "Network activity",
        "timestamp": "1527162615",
        "comment": "",
        "uuid": "00562399-5457-41c3-895a-323d3135ff0f",
        "value": "http://anzo.jp/Client/Invoice-05-21-18/",
        "to_ids": true,
        "type": "url",
        "deleted": false,
        "disable_correlation": false
      },
      {
        "category": "Network activity",
        "timestamp": "1527162621",
        "comment": "",
        "uuid": "4b81dfbc-379b-4b25-91a6-96e164ed03be",
        "value": "http://ezinet.co.za/ACCOUNT/invoice/",
        "to_ids": true,
        "type": "url",
        "deleted": false,
        "disable_correlation": false
      },
      {
        "category": "Network activity",
        "timestamp": "1527162628",
        "comment": "",
        "uuid": "e468770f-a550-4d81-9391-d99d5b703e95",
        "value": "http://detss.com/Client/INV55295737106080394160/",
        "to_ids": true,
        "type": "url",
        "deleted": false,
        "disable_correlation": false
      },
      {
        "category": "Network activity",
        "timestamp": "1527162634",
        "comment": "",
        "uuid": "6c737cdc-7baa-466f-8f23-8d17458b282a",
        "value": "http://jeny.nl/ups.com/WebTracking/IHC-095131093/",
        "to_ids": true,
        "type": "url",
        "deleted": false,
        "disable_correlation": false
      },
      {
        "category": "Network activity",
        "timestamp": "1527162646",
        "comment": "",
        "uuid": "91d464bc-94b6-4cab-9e7a-35b5b8d1618f",
        "value": "http://jeffarchibald.ca/FILE/Invoice-14477606-Invoice-date-052118-Order-no-3568026653/",
        "to_ids": true,
        "type": "url",
        "deleted": false,
        "disable_correlation": false
      },
      {
        "category": "Network activity",
        "timestamp": "1527162653",
        "comment": "",
        "uuid": "d0324ad1-f9ea-4469-8be5-96edf53b383b",
        "value": "https://frankfurter-blumenbote.de/fbb2015/ups.com/WebTracking/VVP-8825990635/",
        "to_ids": true,
        "type": "url",
        "deleted": false,
        "disable_correlation": false
      },
      {
        "category": "Network activity",
        "timestamp": "1527162659",
        "comment": "",
        "uuid": "c71e2259-1dd5-4352-bbd8-c249c16fce1f",
        "value": "http://homexxl.de/images/supplier/ups.com/WebTracking/ZQW-768705390/",
        "to_ids": true,
        "type": "url",
        "deleted": false,
        "disable_correlation": false
      },
      {
        "category": "Network activity",
        "timestamp": "1527162671",
        "comment": "",
        "uuid": "64301f39-148a-4686-bc42-65f3346fb12a",
        "value": "http://czeppel.de/FILE/New-Invoice-FY2348-TA-5179/",
        "to_ids": true,
        "type": "url",
        "deleted": false,
        "disable_correlation": false
      },
      {
        "category": "Network activity",
        "timestamp": "1527162677",
        "comment": "",
        "uuid": "a3f3d972-e413-413a-b0bc-d9cc4d6586d8",
        "value": "http://bmsdesign.com/Client/Payment/",
        "to_ids": true,
        "type": "url",
        "deleted": false,
        "disable_correlation": false
      },
      {
        "category": "Network activity",
        "timestamp": "1527162683",
        "comment": "",
        "uuid": "03874d17-b879-45e7-9b1e-9b0850877fed",
        "value": "https://hillringsberg.com/ups.com/WebTracking/NT-98643761/",
        "to_ids": true,
        "type": "url",
        "deleted": false,
        "disable_correlation": false
      },
      {
        "category": "Network activity",
        "timestamp": "1527162689",
        "comment": "",
        "uuid": "104f8d93-8647-48b8-8d4a-2b07902692c9",
        "value": "http://josephdutton.com/ACCOUNT/Invoice/",
        "to_ids": true,
        "type": "url",
        "deleted": false,
        "disable_correlation": false
      },
      {
        "category": "Network activity",
        "timestamp": "1527162702",
        "comment": "",
        "uuid": "ac1fcec6-873b-4ec9-8910-189302b31619",
        "value": "http://klumpp.me/DOC/Emailing-P161122EO-013518/",
        "to_ids": true,
        "type": "url",
        "deleted": false,
        "disable_correlation": false
      },
      {
        "category": "Network activity",
        "timestamp": "1527162714",
        "comment": "",
        "uuid": "21b312e7-9117-4186-a0dc-55af77e5ac23",
        "value": "http://ergotherapie-gerolstein.de/ups.com/WebTracking/KGE-08714359596985/",
        "to_ids": true,
        "type": "url",
        "deleted": false,
        "disable_correlation": false
      },
      {
        "category": "Network activity",
        "timestamp": "1527162720",
        "comment": "",
        "uuid": "e70ec94e-21fc-42cd-bbe5-6578370de835",
        "value": "http://kursy-bhp-sieradz.pl/pub/DOC/Invoice-313081/",
        "to_ids": true,
        "type": "url",
        "deleted": false,
        "disable_correlation": false
      },
      {
        "category": "Network activity",
        "timestamp": "1527162738",
        "comment": "",
        "uuid": "31913ef8-8981-4464-abdc-e82d0e4bd2e0",
        "value": "http://animematsuri.com/ups.com/WebTracking/JX-63349309/",
        "to_ids": true,
        "type": "url",
        "deleted": false,
        "disable_correlation": false
      },
      {
        "category": "Network activity",
        "timestamp": "1527162751",
        "comment": "",
        "uuid": "8ca846c4-42c9-401a-bddf-d56c38634b65",
        "value": "http://lambertons.com/FILE/New-Invoice-ZK99463-GJ-56124/",
        "to_ids": true,
        "type": "url",
        "deleted": false,
        "disable_correlation": false
      },
      {
        "category": "Network activity",
        "timestamp": "1527162763",
        "comment": "",
        "uuid": "a5beb3ed-267e-47a4-b099-c68a435abc0d",
        "value": "http://coromandelhistory.co.nz/DOC/Direct-Deposit-Notice/",
        "to_ids": true,
        "type": "url",
        "deleted": false,
        "disable_correlation": false
      },
      {
        "category": "Network activity",
        "timestamp": "1527162787",
        "comment": "",
        "uuid": "f360f8f5-4134-46d4-a459-721b92f8abe0",
        "value": "http://kevinlombardo.com/3FB22/",
        "to_ids": true,
        "type": "url",
        "deleted": false,
        "disable_correlation": false
      },
      {
        "category": "Network activity",
        "timestamp": "1527162793",
        "comment": "",
        "uuid": "0cbe40e0-f08e-4486-84bf-27e5aa38c217",
        "value": "http://cabola.com.br/a2VA4q9/",
        "to_ids": true,
        "type": "url",
        "deleted": false,
        "disable_correlation": false
      },
      {
        "category": "Network activity",
        "timestamp": "1527162799",
        "comment": "",
        "uuid": "cffb6f51-ec66-4cfc-ae6d-2e05bb2338a9",
        "value": "http://k8ir.com/xOpouO/",
        "to_ids": true,
        "type": "url",
        "deleted": false,
        "disable_correlation": false
      },
      {
        "category": "Network activity",
        "timestamp": "1527162806",
        "comment": "",
        "uuid": "2ffd9ebc-3f1f-4252-8021-8d6c7bf39a7f",
        "value": "http://franssmanmedia.nl/BdRXyt/",
        "to_ids": true,
        "type": "url",
        "deleted": false,
        "disable_correlation": false
      },
      {
        "category": "Network activity",
        "timestamp": "1527162812",
        "comment": "",
        "uuid": "03c2db94-a978-49d7-a27b-f9f71684b8a9",
        "value": "http://chris-dark.com/lGGPjL/",
        "to_ids": true,
        "type": "url",
        "deleted": false,
        "disable_correlation": false
      }
    ]
  }
}